ocr4all/__init__.py
ocr4all/colors.py
ocr4all/files.py
ocr4all/image_map.py
ocr4all/optional.py
ocr4all_pylib-0.2.6.data/data/requirements.txt
ocr4all_pylib-0.2.6.dist-info/METADATA
ocr4all_pylib-0.2.6.dist-info/WHEEL
ocr4all_pylib-0.2.6.dist-info/top_level.txt
ocr4all_pylib-0.2.6.dist-info/RECORD
