Metadata-Version: 2.1
Name: ocr4all-pylib
Version: 0.2.6
Summary: UNKNOWN
Home-page: https://gitlab2.informatik.uni-wuerzburg.de/ocr4all-page-segmentation/pylib.git
Author: Alexander Gehrke
Author-email: alexander.gehrke@informatik.uni-wuerzburg.de
License: UNKNOWN
Keywords: utility,page segmentation,image preprocessing
Platform: UNKNOWN
Classifier: Programming Language :: Python :: 3
Classifier: License :: OSI Approved :: GNU General Public License v3 or later (GPLv3+)
Classifier: License :: OSI Approved :: Apache Software License
Classifier: Intended Audience :: Science/Research
Classifier: Topic :: Scientific/Engineering :: Image Recognition
Requires-Python: >=3.6
Requires-Dist: numpy (>=1.18.0)
Requires-Dist: pillow (>=7.2.0)
Requires-Dist: setuptools
